variableDatabase/__init__.py
variableDatabase/database.py
variableDatabase-0.0.4.dist-info/LICENSE
variableDatabase-0.0.4.dist-info/METADATA
variableDatabase-0.0.4.dist-info/WHEEL
variableDatabase-0.0.4.dist-info/top_level.txt
variableDatabase-0.0.4.dist-info/RECORD
