Metadata-Version: 2.1
Name: variableDatabase
Version: 0.0.4
Summary: A database package to store variables in an online database for free.
Author: YbicG
Author-email: cjforever2008@gmail.com
Classifier: Programming Language :: Python :: 3
Classifier: License :: OSI Approved :: MIT License
Classifier: Operating System :: OS Independent
Requires-Python: >=3.6
License-File: LICENSE
